TTEkits/model.py
TTEkits-0.2.4.dist-info/LICENSE
TTEkits-0.2.4.dist-info/METADATA
TTEkits-0.2.4.dist-info/WHEEL
TTEkits-0.2.4.dist-info/top_level.txt
TTEkits-0.2.4.dist-info/RECORD
