Metadata-Version: 2.1
Name: TTEkits
Version: 0.2.4
Summary: This is a travel time estimation Python Library!
Home-page: https://github.com/Elon-Lau/TTEkits
Author: Elon Lau
Author-email: weitinglau1999@gmail.com
License: UNKNOWN
Platform: UNKNOWN
Classifier: License :: OSI Approved :: MIT License
Classifier: Programming Language :: Python :: 3.6
Classifier: Programming Language :: Python :: 3.7
Classifier: Programming Language :: Python :: 3.8
License-File: LICENSE
Requires-Dist: gurobipy (>=9.1.0)
Requires-Dist: networkx (>=2.6.3)
Requires-Dist: matplotlib (>=3.3.4)
Requires-Dist: shapely (>=1.8.0)
Requires-Dist: geopandas (>=0.10.2)
Requires-Dist: osmnx (>=1.1.0)
Requires-Dist: pandas (>=1.3.5)
Provides-Extra: dev
